netbox_data_flows/__init__.py
netbox_data_flows/choices.py
netbox_data_flows/constants.py
netbox_data_flows/navigation.py
netbox_data_flows/search.py
netbox_data_flows/urls.py
netbox_data_flows/api/__init__.py
netbox_data_flows/api/urls.py
netbox_data_flows/api/views.py
netbox_data_flows/api/serializers/__init__.py
netbox_data_flows/api/serializers/applications.py
netbox_data_flows/api/serializers/dataflows.py
netbox_data_flows/api/serializers/groups.py
netbox_data_flows/api/serializers/objectaliases.py
netbox_data_flows/filtersets/__init__.py
netbox_data_flows/filtersets/addins.py
netbox_data_flows/filtersets/applications.py
netbox_data_flows/filtersets/dataflows.py
netbox_data_flows/filtersets/filters.py
netbox_data_flows/filtersets/groups.py
netbox_data_flows/filtersets/objectaliases.py
netbox_data_flows/forms/__init__.py
netbox_data_flows/forms/applicationroles.py
netbox_data_flows/forms/applications.py
netbox_data_flows/forms/dataflows.py
netbox_data_flows/forms/fields.py
netbox_data_flows/forms/groups.py
netbox_data_flows/forms/objectaliases.py
netbox_data_flows/migrations/0001_initial.py
netbox_data_flows/migrations/0001_initial_squashed_new_installations.py
netbox_data_flows/migrations/0002_alter_objectalias_options.py
netbox_data_flows/migrations/0002_application_tenant_dataflow_tenant_and_more.py
netbox_data_flows/migrations/0003_allow_port_0_in_source_and_destination_ports.py
netbox_data_flows/migrations/0003_alter_application_custom_field_data_and_more.py
netbox_data_flows/migrations/0004_applicationrole_comments.py
netbox_data_flows/migrations/0004_reindex_netbox_data_flows.py
netbox_data_flows/migrations/0005_add_owner_fields_nb45.py
netbox_data_flows/migrations/0005_dataflowgroup_slug.py
netbox_data_flows/migrations/0006_reindex_netbox_data_flows.py
netbox_data_flows/migrations/0007_remove_objectalias_size.py
netbox_data_flows/migrations/0008_delete_orphaned_aliases.py
netbox_data_flows/migrations/0009_fix_empty_dfg_slugs.py
netbox_data_flows-1.5.0.dist-info/licenses/LICENSE
netbox_data_flows-1.5.0.dist-info/METADATA
netbox_data_flows-1.5.0.dist-info/WHEEL
netbox_data_flows-1.5.0.dist-info/top_level.txt
netbox_data_flows-1.5.0.dist-info/RECORD
