Metadata-Version: 2.4
Name: netbox-data-flows
Version: 1.5.0
Summary: NetBox plugin to document data flows between systems and applications.
Author: Thomas Fargeix
License-Expression: Apache-2.0
Project-URL: Homepage, https://github.com/Alef-Burzmali/netbox-data-flows
Project-URL: Documentation, https://Alef-Burzmali.github.io/netbox-data-flows
Project-URL: Bug Tracker, https://github.com/Alef-Burzmali/netbox-data-flows/issues
Keywords: netbox,netbox-plugins
Classifier: Development Status :: 5 - Production/Stable
Classifier: Environment :: Plugins
Classifier: Programming Language :: Python :: 3 :: Only
Classifier: Programming Language :: Python :: 3.12
Classifier: Programming Language :: Python :: 3.13
Classifier: Programming Language :: Python :: 3.14
Classifier: Topic :: System :: Networking
Requires-Python: >=3.12
License-File: LICENSE
Dynamic: license-file
